kylinpy/__init__.py
kylinpy/cli.py
kylinpy/kylindb.py
kylinpy/kylinpy.py
kylinpy/logger.py
kylinpy/sqla_dialect.py
kylinpy/client/__init__.py
kylinpy/client/client.py
kylinpy/client/exceptions.py
kylinpy/datasource/__init__.py
kylinpy/datasource/_source_interface.py
kylinpy/datasource/cube_source.py
kylinpy/datasource/hive_source.py
kylinpy/utils/__init__.py
kylinpy/utils/compat.py
kylinpy/utils/keywords.py
kylinpy/utils/kylin_types.py
kylinpy/utils/sqla_types.py
tests/__init__.py
tests/test_client.py
tests/test_dialect.py
kylinpy-0.0.999.dev0.dist-info/LICENSE
kylinpy-0.0.999.dev0.dist-info/METADATA
kylinpy-0.0.999.dev0.dist-info/WHEEL
kylinpy-0.0.999.dev0.dist-info/entry_points.txt
kylinpy-0.0.999.dev0.dist-info/top_level.txt
kylinpy-0.0.999.dev0.dist-info/RECORD
