Metadata-Version: 2.1
Name: kylinpy
Version: 0.0.999.dev0
Summary: Apache Kylin Python Client Library
Home-page: https://github.com/Kyligence/kylinpy
Author: Yongjie Zhao
Author-email: yongjie.zhao@kyligence.io
Maintainer: Yongjie Zhao
Maintainer-email: yongjie.zhao@kyligence.io
License: MIT License
Keywords: apache kylin,kylin,kap,kyligence,cli,sqlalchemy dialect
Platform: UNKNOWN
Classifier: Environment :: Console
Classifier: Intended Audience :: Developers
Classifier: License :: OSI Approved :: MIT License
Classifier: Operating System :: OS Independent
Classifier: Programming Language :: Python
Classifier: Programming Language :: Python :: 2.7
Classifier: Programming Language :: Python :: 3.4
Classifier: Programming Language :: Python :: 3.5
Classifier: Programming Language :: Python :: 3.6
Provides-Extra: click
Requires-Dist: click (==6.7); extra == 'click'
Provides-Extra: sqlalchemy
Requires-Dist: sqlalchemy (>=1.1.0); extra == 'sqlalchemy'
